OwaspTop102017ZhongwenbanV13/README.md
OwaspTop102017ZhongwenbanV13/__init__.py
OwaspTop102017ZhongwenbanV13/__main__.py
OwaspTop102017ZhongwenbanV13/file.pdf
OwaspTop102017ZhongwenbanV13/index.html
owasp_top10_2017_zhongwenban_v1_3-2024.3.5.0.dist-info/METADATA
owasp_top10_2017_zhongwenban_v1_3-2024.3.5.0.dist-info/WHEEL
owasp_top10_2017_zhongwenban_v1_3-2024.3.5.0.dist-info/entry_points.txt
owasp_top10_2017_zhongwenban_v1_3-2024.3.5.0.dist-info/top_level.txt
owasp_top10_2017_zhongwenban_v1_3-2024.3.5.0.dist-info/RECORD
